helloworld.py
helloworld_mja_202106-0.0.1.dist-info/LICENSE.txt
helloworld_mja_202106-0.0.1.dist-info/METADATA
helloworld_mja_202106-0.0.1.dist-info/WHEEL
helloworld_mja_202106-0.0.1.dist-info/top_level.txt
helloworld_mja_202106-0.0.1.dist-info/RECORD
